pyluxa4/__init__.py
pyluxa4/__main__.py
pyluxa4/__meta__.py
pyluxa4/cli.py
pyluxa4/client.py
pyluxa4/common.py
pyluxa4/hid.py
pyluxa4/scheduler.py
pyluxa4/server.py
pyluxa4/usb.py
pyluxa4-1.7.dist-info/METADATA
pyluxa4-1.7.dist-info/WHEEL
pyluxa4-1.7.dist-info/licenses/LICENSE.md
pyluxa4-1.7.dist-info/RECORD
